pi_pkg/__init__.py
pi_pkg/pi.py
pi_pkg-0.1.0.dist-info/LICENSE
pi_pkg-0.1.0.dist-info/METADATA
pi_pkg-0.1.0.dist-info/WHEEL
pi_pkg-0.1.0.dist-info/entry_points.txt
pi_pkg-0.1.0.dist-info/top_level.txt
pi_pkg-0.1.0.dist-info/RECORD
