Metadata-Version: 2.1
Name: pi-pkg
Version: 0.1.0
Summary: 计算pi的小程序
Home-page: https://github.com/pypa/sampleproject
Author: zhangjiong
Author-email: 49005718@qq.com
License: MIT
Platform: UNKNOWN
